[
    {
      "contract_id": 1,
      "clientName": "Jan",
      "clientSurname": "Mentz",
      "clientEmail": "janmen777@gmail.com",
      "clientPhone": "0769616131",
      "typeofjob": "IT",
      "contracttype": "Maintenance",
      "timePeriod": "6",
      "startDate": "2024-01-15",
      "contractname": "Contract 1",
      "location": "Montana",
      "assigned": "Xander Glanninger",
      "finished": false
    },
    {
      "contract_id": 2,
      "clientName": "Vernon",
      "clientSurname": "Engelbrecht",
      "clientEmail": "janmen777@gmail.com",
      "clientPhone": "0769616131",
      "typeofjob": "IT",
      "contracttype": "Maintenance",
      "timePeriod": "6",
      "startDate": "2024-01-15",
      "contractname": "Contract 2",
      "location": "Pretoria North",
      "assigned": "Jan Albert",
      "finished": false
    },
    {
      "contract_id": 3,
      "clientName": "Pieter",
      "clientSurname": "Kriel",
      "clientEmail": "janmen777@gmail.com",
      "clientPhone": "0823092972",
      "typeofjob": "Repair",
      "contracttype": "Maintenance",
      "timePeriod": "7",
      "startDate": "2024-10-08",
      "contractname": "Light fix",
      "location": "Montana",
      "assigned": "Sean Botha",
      "finished": false
    },
    {
      "clientName": "Pieter",
      "clientSurname": "Kriel",
      "clientEmail": "janmen777@gmail.com",
      "clientPhone": "0823092972",
      "typeofjob": "IT",
      "contracttype": "Once Off",
      "timePeriod": "7",
      "startDate": "2024-10-18",
      "contractname": "Light Instalation",
      "location": "Pretoria North",
      "assigned": "Dylan Cheballah",
      "finished": false
    },
    {
      "clientName": "Jan",
      "clientSurname": "Doe",
      "clientEmail": "janmen777@gmail.com",
      "clientPhone": "21436789",
      "typeofjob": "Big PP business",
      "contracttype": "Once Off",
      "timePeriod": "12",
      "startDate": "2024-10-17",
      "contractname": "Need a big PP",
      "location": "Montana",
      "assigned": "Pieter Marits",
      "finished": false
    },
    {
      "clientName": "Jane",
      "clientSurname": "Mentz",
      "clientEmail": "jane@gmail.com",
      "clientPhone": "123456789",
      "typeofjob": "She need some MILK",
      "contracttype": "Once Off",
      "timePeriod": "12",
      "startDate": "2024-10-24",
      "contractname": "Fill her up",
      "location": "Montana",
      "assigned": "Leo Glanninger",
      "finished": false
    }
  ]
